maxbridge/__init__.py
maxbridge/commandmanager.py
maxbridge/debugger.py
maxbridge/menuitem.py
maxbridge/menuitemtype.py
maxbridge/pathmanager.py
maxbridge/scriptmanager.py
maxbridge/supportversiontype.py
maxbridge-0.0.15.dist-info/LICENSE
maxbridge-0.0.15.dist-info/METADATA
maxbridge-0.0.15.dist-info/WHEEL
maxbridge-0.0.15.dist-info/entry_points.txt
maxbridge-0.0.15.dist-info/top_level.txt
maxbridge-0.0.15.dist-info/RECORD
