Metadata-Version: 2.1
Name: maxbridge
Version: 0.0.15
Summary: Autodesk 3ds Max to Python Bridge.
Home-page: https://ddukbaek2.com
Author: ddukbaek2
Author-email: ddukbaek2@gmail.com
Classifier: Programming Language :: Python :: 3
Classifier: License :: OSI Approved :: MIT License
Classifier: Operating System :: Microsoft :: Windows
Requires-Python: >=3.9.7
License-File: LICENSE
Requires-Dist: ptvsd
Requires-Dist: xid-xpl
